<?xml version="1.0" encoding="UTF-8"?>
<figure id="example46" class="code">
<pre><code><span style="color: #000096;">&lt;w</span> <span style="color: #f5844c">cligs:form=</span><span style="color: #993300;">"comenzó"</span> <span style="color: #f5844c">lemma=</span><span style="color: #993300;">"comenzar"</span> <span style="color: #f5844c">cligs:tag=</span><span style="color: #993300;">"VMIS3S0"</span> <span style="color: #f5844c">cligs:ctag=</span><span style="color: #993300;">"VMI"</span> 
  <span style="color: #f5844c">pos=</span><span style="color: #993300;">"verb"</span> <span style="color: #f5844c">type=</span><span style="color: #993300;">"main"</span> <span style="color: #f5844c">cligs:mood=</span><span style="color: #993300;">"indicative"</span> <span style="color: #f5844c">cligs:tense=</span><span style="color: #993300;">"past"</span> <span style="color: #f5844c">cligs:person=</span><span style="color: #993300;">"3"</span> 
  <span style="color: #f5844c">cligs:num=</span><span style="color: #993300;">"singular"</span> <span style="color: #f5844c">cligs:wnsyn=</span><span style="color: #993300;">"00348746-v"</span> <span style="color: #f5844c">cligs:wnlex=</span><span style="color: #993300;">"verb.change"</span><span style="color: #000096;">&gt;</span>comenzó<span style="color: #000096;">&lt;/w&gt;</span>
<span style="color: #000096;">&lt;w</span> <span style="color: #f5844c">cligs:form=</span><span style="color: #993300;">"a"</span> <span style="color: #f5844c">lemma=</span><span style="color: #993300;">"a"</span> <span style="color: #f5844c">cligs:tag=</span><span style="color: #993300;">"SP"</span> <span style="color: #f5844c">cligs:ctag=</span><span style="color: #993300;">"SP"</span> <span style="color: #f5844c">pos=</span><span style="color: #993300;">"adposition"</span> 
  <span style="color: #f5844c">type=</span><span style="color: #993300;">"preposition"</span> <span style="color: #f5844c">cligs:wnsyn=</span><span style="color: #993300;">"xxx"</span> <span style="color: #f5844c">cligs:wnlex=</span><span style="color: #993300;">"xxx"</span><span style="color: #000096;">&gt;</span>a<span style="color: #000096;">&lt;/w&gt;</span>
<span style="color: #000096;">&lt;w</span> <span style="color: #f5844c">cligs:form=</span><span style="color: #993300;">"hablar"</span> <span style="color: #f5844c">lemma=</span><span style="color: #993300;">"hablar"</span> <span style="color: #f5844c">cligs:tag=</span><span style="color: #993300;">"VMN0000"</span> <span style="color: #f5844c">cligs:ctag=</span><span style="color: #993300;">"VMN"</span> <span style="color: #f5844c">pos=</span><span style="color: #993300;">"verb"</span> 
  <span style="color: #f5844c">type=</span><span style="color: #993300;">"main"</span> <span style="color: #f5844c">cligs:mood=</span><span style="color: #993300;">"infinitive"</span> <span style="color: #f5844c">cligs:wnsyn=</span><span style="color: #993300;">"xxx"</span> <span style="color: #f5844c">cligs:wnlex=</span><span style="color: #993300;">"xxx"</span><span style="color: #000096;">&gt;</span>hablar<span style="color: #000096;">&lt;/w&gt;</span>
<span style="color: #000096;">&lt;w</span> <span style="color: #f5844c">cligs:form=</span><span style="color: #993300;">"nos"</span> <span style="color: #f5844c">lemma=</span><span style="color: #993300;">"nos"</span> <span style="color: #f5844c">cligs:tag=</span><span style="color: #993300;">"PP1CP00"</span> <span style="color: #f5844c">cligs:ctag=</span><span style="color: #993300;">"PP"</span> <span style="color: #f5844c">pos=</span><span style="color: #993300;">"pronoun"</span> 
  <span style="color: #f5844c">type=</span><span style="color: #993300;">"personal"</span> <span style="color: #f5844c">cligs:person=</span><span style="color: #993300;">"1"</span> <span style="color: #f5844c">cligs:gen=</span><span style="color: #993300;">"common"</span> <span style="color: #f5844c">cligs:num=</span><span style="color: #993300;">"plural"</span> 
  <span style="color: #f5844c">cligs:wnsyn=</span><span style="color: #993300;">"xxx"</span> <span style="color: #f5844c">cligs:wnlex=</span><span style="color: #993300;">"xxx"</span><span style="color: #000096;">&gt;</span>nos<span style="color: #000096;">&lt;/w&gt;</span></code></pre>
<figcaption>Example 46: FreeLing output for verb forms with enclitic pronouns (in CLiGS TEI-format).</figcaption>
</figure>
